dmm/__init__.py
dmm/dmm.py
dmm-0.0.1.dist-info/METADATA
dmm-0.0.1.dist-info/WHEEL
dmm-0.0.1.dist-info/top_level.txt
dmm-0.0.1.dist-info/RECORD
