Metadata-Version: 2.1
Name: dmm
Version: 0.0.1
Summary: DMM API Client for Python
Home-page: https://github.com/matz1ppei/dmm
Author: Ippei Matsubara
Author-email: matz1ppei@gmail.com
License: UNKNOWN
Platform: UNKNOWN
Classifier: Programming Language :: Python :: 3
Classifier: License :: OSI Approved :: MIT License
Requires-Dist: requests
